Metadata-Version: 2.1
Name: PySIC
Version: 1.0.0
Summary: A package for satellite image classification using machine learning models
Home-page: https://github.com/Hejarshahabi
Author: Hejar Shahabi
Author-email: hejarshahabi@gmail.com
License: MIT
Keywords: Machine Learning,Remote Sensing
Platform: UNKNOWN
Classifier: Development Status :: 5 - Production/Stable
Classifier: Intended Audience :: Science/Research
Classifier: Operating System :: Microsoft :: Windows :: Windows 10
Classifier: License :: OSI Approved :: MIT License
Classifier: Programming Language :: Python :: 3
